bitcoinde/__init__.py
bitcoinde/trading_api.py
bitcoinde/config/api.cfg
bitcoinde-0.0.1a0.dist-info/LICENSE
bitcoinde-0.0.1a0.dist-info/METADATA
bitcoinde-0.0.1a0.dist-info/WHEEL
bitcoinde-0.0.1a0.dist-info/top_level.txt
bitcoinde-0.0.1a0.dist-info/RECORD
