Metadata-Version: 2.1
Name: bitcoinde
Version: 0.0.1a0
Summary: Python wrapper for the bitcoin.de trading API
Home-page: UNKNOWN
Author: Riccardo Bucco
Author-email: riccardobucco@gmail.com
License: MIT License
Platform: UNKNOWN
Classifier: Development Status :: 3 - Alpha
Classifier: Intended Audience :: Developers
Classifier: License :: OSI Approved :: MIT License
Requires-Dist: requests
